login_history/__init__.py
login_history/admin.py
login_history/apps.py
login_history/models.py
login_history/settings.py
login_history/tests.py
login_history/urls.py
login_history/views.py
login_history/migrations/0001_initial.py
login_history/migrations/0002_loginhistory_is_login.py
login_history/migrations/0003_alter_loginhistory_id.py
login_history/migrations/0004_alter_loginhistory_ip.py
login_history/migrations/__init__.py
dj_user_login_history-1.0.6.dist-info/LICENSE
dj_user_login_history-1.0.6.dist-info/METADATA
dj_user_login_history-1.0.6.dist-info/WHEEL
dj_user_login_history-1.0.6.dist-info/top_level.txt
dj_user_login_history-1.0.6.dist-info/RECORD
