Metadata-Version: 2.1
Name: dj-user-login-history
Version: 1.0.6
Summary: Django app which keep track of user login history.
Home-page: https://github.com/farhad0085/dj-user-login-history
Author: Farhad Hossain
Author-email: farhadhossain0085@gmail.com
License: MIT
Classifier: License :: OSI Approved :: MIT License
Classifier: Programming Language :: Python :: 3
Classifier: Programming Language :: Python :: 3.6
License-File: LICENSE
Requires-Dist: django (>=2.2)
